{
  "summary_type": "user_daily",
  "generation_time": "2026-02-22T01:37:33.971470",
  "tweet_count": 54,
  "summary": "## 核心动态\n- FSD 与 Starlink 被提出将推动“游牧”生活方式：他认同该预测，认为自动驾驶+卫星连接会在5–10年内降低城市化并改变教育与居住模式。  \n- SpaceX 与 xAI 的长期太空计算愿景被广泛转发讨论：关联轨道数据中心、月球制造与大规模卫星发射，强调太空中低成本 AI 计算的战略意义。  \n- 强烈要求公开 Epstein 文件并推动起诉：多条转发/评论指责对涉案富豪未被追责，持续呼吁司法介入与透明度。\n\n## 值得关注\n- Grok / Grokipedia 热度迅速上升：多条转发声称下载、引用和市场份额激增，平台增长被强调为“爆发式”。  \n- Grok 已整合入 X Chat：新增“Ask Grok”功能，显示社交与对话 AI 的进一步融合。  \n- Starlink 商业落地进展：菲律宾最大运营商承诺用 Direct-to-Cell 实现全国覆盖，标志卫星直连移动的商业化推进。  \n- Starlink Mini 与便携化宣传频繁出现：在极端环境中可用的案例被多次转发，凸显产品可用性。  \n- Tesla FSD 能识别手势：FSD 在窄道场景对手势的响应被展示，体现感知和交互能力提升。  \n- Grok 在金融实盘测试中表现亮眼：转发宣称 Grok4 明显跑赢标普，引发对 AI 投资策略的讨论。  \n- 招聘取向直白：关于 Dojo 3 的招聘帖强调“无需学位、看解决问题能力”，反映特斯拉以能力为主的用人偏好。  \n- 2026 年 AGI 预测继续被引用：多条转发与短评重复他或他人对 2026 年出现 AGI 的判断。  \n- 政治与社会议题频繁互动：投票身份证、移民、情报机构撤回报告等话题被大量转发并引发争论。  \n- 对欧洲生育率的担忧被强调：转发称欧洲人口低迷是根本性风险，反映对人口结构问题的关注。  \n- 平台言论自由与偏见论调并行：多条转发支持“取消审查”、批评主流 AI 的政治偏见，体现 X 内部舆论方向。  \n- 互动风格极简且高频：大量单字/单词回应（如 “True”、“Nope”、“Good” 等）显示以快速认同/否定参与大量话题。",
  "metadata": {
    "original_tweets": 26,
    "retweets": 28,
    "media_tweets": 6,
    "data_hash": "8ca4a01a",
    "user": "elonmusk"
  }
}