{
  "summary_type": "user_daily",
  "generation_time": "2026-04-12T01:37:23.598723",
  "tweet_count": 28,
  "summary": "## 核心动态\n- xAI / Grok 的亮相与进展：多条推文围绕 Grok（包括“Grok 很好笑”和“Grok 救了猫”的故事），并转发了关于 Grok 4.20 在 IFBench 以 81% 夺冠的讨论，凸显他继续推动自家 AI 能力与品牌化叙事。  \n- 对美国载人登月与航天的支持：多次引用/转发 NASA、White House 和宇航员消息，庆祝 Artemis II 安全着水并强调“下一步：火星”，表现出对载人深空探索的宣传与激情。  \n- SpaceX / Starlink 与 Falcon 发射节奏：转发并宣传当日多次 Falcon 9 发射（含 25 颗 Starlink 卫星），以及“Falcon has landed”的回收视频，突显高频发射与星链规模增长的成就。  \n- 特斯拉产品与自动驾驶推广：公开称赞 Cybertruck 为“迄今最佳产品”，并转发 FSD 在荷兰推送及 FSD 比人类更安全的论断，继续为车辆与全自动驾驶做口碑背书。\n\n## 值得关注\n- Grok 的正负面叙事并存：既有幽默/救命的温情故事，也有以基准赛榜首为卖点的技术宣传，形成“能力+人情”双重叙事。  \n- IFBench 数据点被放大：Grok 4.20 的“81%”与“#1”标签在转发中反复出现，作为可靠性与指令遵循能力的佐证。  \n- Artemis II 相关推文互动极高（NASA 与 White House 原推获得大量点赞/转发），Musk 的“Welcome home!”式转发明显放大官方庆祝。  \n- Starlink 活跃卫星数突破报道（推文里提到 >10,225）以及“当天两次 Falcon 发射”被强调，暗示商业化部署与发射节奏作为重要绩效指标。  \n- “Falcon has landed”附带高质量视频，提高可视传播效果，有利于塑造回收成功的公众印象。  \n- 特斯拉方面：Cybertruck 的用户体验评价被浓缩为强烈推荐，FSD 在荷兰的实际下放和“~9x 更安全、未来 1000x”类比话术都在为监管与市场接受铺路。  \n- 平台治理与商业策略信号：转发了 X 产品负责人关于“聚合器补贴降至 60%、对惯性诱饵内容进一步扣减”的说明，显示平台在调整内容补偿机制。  \n- 政治/社会议题的放大器作用：多条转发涉及争议性政治内容（爱尔兰示威、澳洲拘捕、选举舞弊案等），表明账号仍在放大保守派和争议议题的流量。  \n- 关于公共安全政策的简短表态：引用“谋杀者登记”等建议并以“重犯率高、对社区安全重要”作支持，露出对刑事政策的介入力度。  \n- 互动节奏：多条原始推文与转发在不同主题间快速切换（AI、航天、汽车、政治），体现覆盖面广且以转发为主的传播策略。",
  "metadata": {
    "original_tweets": 9,
    "retweets": 19,
    "media_tweets": 6,
    "data_hash": "925283fb",
    "user": "elonmusk"
  }
}