{
  "user": {
    "screen_name": "aleabitoreddit",
    "name": "Serenity",
    "description": "That famous @Reddit WSB Trader now on X. \n\nAI/Semi Supply Chain Analyst\n\nex. RISC-V FDN, AI research scientist; now trading unknown bottlenecks.",
    "followers_count": 209102,
    "verified": false,
    "is_blue_verified": true
  },
  "date": "20260403",
  "last_updated": "2026-04-20T17:34:50.181596",
  "tweet_count": 7,
  "tweets": [
    {
      "id": "2039887575520026653",
      "text": "Applied Optoelectronics ( $AAOI ) said it received a new $71 million order from its hyperscaler customer today.\n\nThe orders flowing in are endless.\n\nIf they become the largest 800G/1.6T capacity in the US and optical demand does take off.\n\nThe revenue translation would be pretty insane.",
      "created_at": "Fri Apr 03 02:07:51 +0000 2026",
      "lang": "en",
      "media": [
        {
          "type": "photo",
          "id": "2039887504451780608",
          "url": "https://pbs.twimg.com/media/HE8i4KSbQAAyRWM.jpg"
        }
      ],
      "retweet": null,
      "quoted": null,
      "stats": {
        "retweet_count": 44,
        "favorite_count": 669,
        "reply_count": 42,
        "quote_count": 6
      }
    },
    {
      "id": "2039894556871913726",
      "text": "If you want exposure to memory, $DRAM is a genuinely great ETF.\n\nI normally don't praise ETFs, but this is solid.\n\n1. $MU - 24.63%\n2. Samsung - 24.11%\n3. SK Hynix - 23.08%\n4. $SNDK  - 4.9%\n5. Kioxia - 4.86%\n6. $WDC - 4.77%\n7. Nanya - 3.89%\n8. Winbond - 2.4%\n\nDisclosure: Friends over at @roundhill did reach out about the launch, but I'm not getting paid to say this (just in case you think this random post is sponsored, it's not). \n\nJust a genuinely great ETF for memory exposure if you don't have access to foreign stocks. \n\nAnd I’d encourage more institutions to make ETFs like this.",
      "created_at": "Fri Apr 03 02:35:36 +0000 2026",
      "lang": "en",
      "media": [
        {
          "type": "photo",
          "id": "2039894550274314240",
          "url": "https://pbs.twimg.com/media/HE8pSSBbEAAIwvM.jpg"
        }
      ],
      "retweet": null,
      "quoted": null,
      "stats": {
        "retweet_count": 150,
        "favorite_count": 1608,
        "reply_count": 91,
        "quote_count": 19
      }
    },
    {
      "id": "2039906072291611057",
      "text": "Serenity's Followers Favorite Stock Parabolic Growth ETF:\n\nThe most anticipated ETF of all time:\n\n$TRT - $5.88\n$HGRAF - $4.49\n$SIVE - 9.9 SEK\n$QURE - $17.21\n$AEHR - $45.08\n$ENVX - $5.07\n$ASPI - $4.2\n$EONR - $11.79\n$LPK.DE - 6.59 EUR\n$MITK - $13.9\n$EQR.AX - .315 AUD\n$WATT - $15.8\n$VLN - $1.16\n$BZAI - $1.79\n$TMC - $4.59\n$ALCJ - $74.57\n$POET - $6.11\n$AAOI - $108.86\n$ADUR - $10.37\n$P4O.DE - 6.85 EUR\n$PLAB - $40.87\n$FLY - $33.16\n$LASR - $60.7\n$AL2SI - 28.70 EUR\n$ENAFF - $1.71\n$VPG - $44.7\n$EOS.AX - $9.00\n\nI haven't heard of 1/3rd of these names, but if my followers have high conviction that their name will 10x...\n\nSo do I.",
      "created_at": "Fri Apr 03 03:21:21 +0000 2026",
      "lang": "en",
      "media": [
        {
          "type": "photo",
          "id": "2039906066125987840",
          "url": "https://pbs.twimg.com/media/HE8zwl6aoAAhi-H.jpg"
        },
        {
          "type": "photo",
          "id": "2039906066142736384",
          "url": "https://pbs.twimg.com/media/HE8zwl-aMAAnl5I.jpg"
        }
      ],
      "retweet": null,
      "quoted": {
        "id": "2039685700044628243",
        "text": "Okay chat. I'm curious what your thoughts are on the next 1350%+ 1Y return $SNDK or 2918% 1Y return $AXTI. \n\nIf you have to choose 1 very high conviction, hyperbolic growth stock...\n\nWhat would it be and why?",
        "created_at": "Thu Apr 02 12:45:41 +0000 2026",
        "lang": "en",
        "media": [],
        "retweet": null,
        "quoted": null,
        "user": {
          "id": "1940360837547565056",
          "name": "Serenity",
          "screen_name": "aleabitoreddit",
          "description": "That famous @Reddit WSB Trader now on X. \n\nAI/Semi Supply Chain Analyst\n\nex. RISC-V FDN, AI research scientist; now trading unknown bottlenecks.",
          "followers_count": 208943,
          "friends_count": 107,
          "verified": false,
          "is_blue_verified": true
        },
        "stats": {
          "retweet_count": 23,
          "favorite_count": 645,
          "reply_count": 172,
          "quote_count": 2
        }
      },
      "stats": {
        "retweet_count": 63,
        "favorite_count": 985,
        "reply_count": 70,
        "quote_count": 8
      }
    },
    {
      "id": "2039927381914489301",
      "text": "Aside from Snapchat, maybe…\n\n$ASST, $IREN, $BKKT?\n\nThere happens to be a common denominator sitting on Iren’s Board of Directors.\n\nFamous for dumping excessive ATMs on retail investors. https://t.co/qGCWsGIGXD",
      "created_at": "Fri Apr 03 04:46:02 +0000 2026",
      "lang": "en",
      "media": [
        {
          "type": "photo",
          "id": "2039927375857881088",
          "url": "https://pbs.twimg.com/media/HE9HI-2akAAILsC.jpg"
        }
      ],
      "retweet": null,
      "quoted": {
        "id": "2039846458619490681",
        "text": "@stockgeekTV @IrenicCap @RandianCapital @BoxLongs Has any company in the history of capitalism ever been ran as focused on enriching the insiders at the expense of external shareholders more than this one?",
        "created_at": "Thu Apr 02 23:24:28 +0000 2026",
        "lang": "en",
        "media": [],
        "retweet": null,
        "quoted": null,
        "user": {
          "id": "49774820",
          "name": "tyler hogge",
          "screen_name": "thogge",
          "description": "startup helper. \n\nthere are no beliefs; only actions.",
          "followers_count": 29679,
          "friends_count": 397,
          "verified": false,
          "is_blue_verified": true
        },
        "stats": {
          "retweet_count": 1,
          "favorite_count": 97,
          "reply_count": 16,
          "quote_count": 2
        }
      },
      "stats": {
        "retweet_count": 15,
        "favorite_count": 367,
        "reply_count": 61,
        "quote_count": 1
      }
    },
    {
      "id": "2040001386788815245",
      "text": "I still find it interesting you can disrupt the trillion dollar Western AI Buildout…\n\nFor a total price tag of ~$600m.\n\nCan anyone guess the companies? https://t.co/GvardDu5bN",
      "created_at": "Fri Apr 03 09:40:06 +0000 2026",
      "lang": "en",
      "media": [
        {
          "type": "photo",
          "id": "2040001381302767616",
          "url": "https://pbs.twimg.com/media/HE-KcqnbkAA6cmz.jpg"
        }
      ],
      "retweet": null,
      "quoted": null,
      "stats": {
        "retweet_count": 8,
        "favorite_count": 453,
        "reply_count": 80,
        "quote_count": 3
      }
    },
    {
      "id": "2040023134095471044",
      "text": "I just realized… hit 5,118.02% returns last week.\n\n5000%+ not too bad in <2 years?\n\nHard to keep up with $5 footlong sandwich inflation even after front running:\n\n-> $MSTR for halving\n-> $RKLB and $HOOD for space/fintech rally\n-> $GOOGL and $TSM for large cap rally\n-> Samsung, SK Hynix, Asian equities for memory\n-> $LITE, $AXTI, and $COHR for EML/photonics\n-> $SOI, $SIVE, $AEHR, $TSEM, Win for CW/SiPH/CPO.\n\nSome side quests here and there with Venezuelan natural resource companies and drones (that didn’t turn out as well).\n\nBut generally market read has been decent so far on what’s coming next.\n\nAnd I do think scale up photonics is next, especially focusing on CW laser companies, substrates, testing and foundries.",
      "created_at": "Fri Apr 03 11:06:31 +0000 2026",
      "lang": "en",
      "media": [
        {
          "type": "photo",
          "id": "2040023126231453696",
          "url": "https://pbs.twimg.com/media/HE-eOYybkAAMJDv.jpg"
        }
      ],
      "retweet": null,
      "quoted": {
        "id": "2039248989946794374",
        "text": "Modest +1,124.09% return over the past year.\n\nAnon, only a few years left to escape the permanent underclass due to AI?\n\nOpenAI raising $122B is enough to fuel the rally for another 2 years.\n\nAnd new supercycles from photonics < $SIVE to $AAOI >, testing with $AEHR, $NBIS DCs, and advanced packing from $AMKR to $POET.\n\nIs just getting started.",
        "created_at": "Wed Apr 01 07:50:21 +0000 2026",
        "lang": "en",
        "media": [
          {
            "type": "photo",
            "id": "2039248984364244992",
            "url": "https://pbs.twimg.com/media/HEzeJZmbYAAH57f.jpg"
          }
        ],
        "retweet": null,
        "quoted": null,
        "user": {
          "id": "1940360837547565056",
          "name": "Serenity",
          "screen_name": "aleabitoreddit",
          "description": "That famous @Reddit WSB Trader now on X. \n\nAI/Semi Supply Chain Analyst\n\nex. RISC-V FDN, AI research scientist; now trading unknown bottlenecks.",
          "followers_count": 208943,
          "friends_count": 107,
          "verified": false,
          "is_blue_verified": true
        },
        "stats": {
          "retweet_count": 63,
          "favorite_count": 1343,
          "reply_count": 101,
          "quote_count": 10
        }
      },
      "stats": {
        "retweet_count": 47,
        "favorite_count": 1157,
        "reply_count": 102,
        "quote_count": 4
      }
    },
    {
      "id": "2040114262358839644",
      "text": "I got cited by Bezinga today after I made fun of Jim Cramer.\n\nThey included my quote: “Thanks for saving $MSFT Jim”.\n\nBut in the title they called me a Meme Trader…\n\nI didn’t know all my longs in AI supply chain bottlenecks from $AXTI to $LITE were memes?\n\nAlways appreciate the news coverage though… especially if it’s comments around Cramer on Bezinga or Burry on Yahoo Finance.",
      "created_at": "Fri Apr 03 17:08:38 +0000 2026",
      "lang": "en",
      "media": [
        {
          "type": "photo",
          "id": "2040114255631200256",
          "url": "https://pbs.twimg.com/media/HE_xG0QbsAADY0S.jpg"
        },
        {
          "type": "photo",
          "id": "2040114255635374080",
          "url": "https://pbs.twimg.com/media/HE_xG0RbYAAV6hz.jpg"
        }
      ],
      "retweet": null,
      "quoted": null,
      "stats": {
        "retweet_count": 13,
        "favorite_count": 545,
        "reply_count": 55,
        "quote_count": 0
      }
    }
  ]
}