{
  "user": {
    "screen_name": "dotey",
    "name": "宝玉",
    "description": "Prompt Engineer, dedicated to learning and disseminating knowledge about AI, software engineering, and engineering management.",
    "followers_count": 200989,
    "verified": false,
    "is_blue_verified": true
  },
  "date": "20260323",
  "last_updated": "2026-03-23T04:46:36.013632",
  "tweet_count": 1,
  "tweets": [
    {
      "id": "2035917916269387831",
      "text": "https://t.co/0M8A3oXboc",
      "created_at": "Mon Mar 23 03:13:51 +0000 2026",
      "lang": "zxx",
      "media": [],
      "retweet": null,
      "quoted": null,
      "stats": {
        "retweet_count": 9,
        "favorite_count": 83,
        "reply_count": 5,
        "quote_count": 2
      }
    }
  ]
}