{
  "user": {
    "screen_name": "elonmusk",
    "name": "Elon Musk",
    "description": "",
    "followers_count": 235835186,
    "verified": false,
    "is_blue_verified": true
  },
  "date": "20260228",
  "last_updated": "2026-03-03T20:09:50.968706",
  "tweet_count": 12,
  "tweets": [
    {
      "id": "2027547187174076536",
      "text": "RT @Starlink: Starlink Direct to Cell is now available in the UK and will provide data with voice, video and messaging to customers in area…",
      "created_at": "Sat Feb 28 00:51:34 +0000 2026",
      "lang": "en",
      "media": [],
      "retweet": {
        "id": "2027528623994114297",
        "text": "Starlink Direct to Cell is now available in the UK and will provide data with voice, video and messaging to customers in areas with no terrestrial service",
        "created_at": "Fri Feb 27 23:37:48 +0000 2026",
        "lang": "en",
        "media": [],
        "retweet": null,
        "quoted": {
          "id": "2026946266739916916",
          "text": "NEWS: We’ve become the first UK network to switch on direct-to-device satellite connectivity 🛰️ \n\nEnabling our customers to stay connected in areas with no traditional mobile coverage, O2 Satellite automatically connects in areas with no cellular coverage. \n\nFrom today, O2 Satellite supports text messaging and data across apps including WhatsApp, Messenger and Google Maps – providing an additional layer of reassurance when customers move to areas beyond traditional mobile coverage. \n\nCustomers can opt-in to O2 Satellite as a £3-per-month bolt-on – and will be included at no extra cost for Ultimate Plan customers in the coming weeks 📲 \n\nPress release 👉 https://t.co/qNfcmeVofF",
          "created_at": "Thu Feb 26 09:03:43 +0000 2026",
          "lang": "en",
          "media": [
            {
              "type": "photo",
              "id": "2026946245642575872",
              "url": "https://pbs.twimg.com/media/HCEo3wZWYAAa-O7.jpg"
            }
          ],
          "retweet": null,
          "quoted": null,
          "user": {
            "id": "1393246281053638662",
            "name": "Virgin Media O2 News",
            "screen_name": "VMO2News",
            "description": "We’re Virgin Media O2 and we’re here to upgrade the UK. Follow us for latest news, director updates, and more from #TeamVirginMediaO2.",
            "followers_count": 5012,
            "friends_count": 850,
            "verified": false,
            "is_blue_verified": true
          },
          "stats": {
            "retweet_count": 29,
            "favorite_count": 173,
            "reply_count": 43,
            "quote_count": 5
          }
        },
        "user": {
          "id": "1330170106501079041",
          "name": "Starlink",
          "screen_name": "Starlink",
          "description": "Fast, affordable internet available all around the world. Engineered by @SpaceX",
          "followers_count": 1554140,
          "friends_count": 30,
          "verified": false,
          "is_blue_verified": true
        },
        "stats": {
          "retweet_count": 455,
          "favorite_count": 2426,
          "reply_count": 406,
          "quote_count": 31
        }
      },
      "quoted": null,
      "stats": {
        "retweet_count": 455,
        "favorite_count": 0,
        "reply_count": 0,
        "quote_count": 0
      }
    },
    {
      "id": "2027590141964144814",
      "text": "RT @xAIMemphis: Had a great time hosting  @MarshaBlackburn and @SenBrentTaylor today at MACROHARD. \n\nWe showed them how @xai is keeping uti…",
      "created_at": "Sat Feb 28 03:42:15 +0000 2026",
      "lang": "en",
      "media": [],
      "retweet": {
        "id": "2027550338866086269",
        "text": "Had a great time hosting  @MarshaBlackburn and @SenBrentTaylor today at MACROHARD. \n\nWe showed them how @xai is keeping utility costs down for the community while building the world's largest AI supercomputer.\n\nWe appreciate their support. https://t.co/2UoA7Z84EI",
        "created_at": "Sat Feb 28 01:04:05 +0000 2026",
        "lang": "en",
        "media": [
          {
            "type": "photo",
            "id": "2027550330079100928",
            "url": "https://pbs.twimg.com/media/HCNOSGSXQAAsvn4.jpg"
          }
        ],
        "retweet": null,
        "quoted": null,
        "user": {
          "id": "1937236128010240001",
          "name": "xAI Memphis",
          "screen_name": "xAIMemphis",
          "description": "",
          "followers_count": 23726,
          "friends_count": 53,
          "verified": false,
          "is_blue_verified": true
        },
        "stats": {
          "retweet_count": 213,
          "favorite_count": 1655,
          "reply_count": 171,
          "quote_count": 10
        }
      },
      "quoted": null,
      "stats": {
        "retweet_count": 212,
        "favorite_count": 0,
        "reply_count": 0,
        "quote_count": 0
      }
    },
    {
      "id": "2027630872569241888",
      "text": "RT @MarioNawfal: SpaceX Starbase just dropped the coolest parade float Brownsville has ever seen, a glowing rocket with the full SPACEX log…",
      "created_at": "Sat Feb 28 06:24:06 +0000 2026",
      "lang": "en",
      "media": [],
      "retweet": {
        "id": "2027603290687426647",
        "text": "SpaceX Starbase just dropped the coolest parade float Brownsville has ever seen, a glowing rocket with the full SPACEX logo lighting up the night during Charro Days.\n\nFifth year running and it's awesome.\nhttps://t.co/i98aJgMgdi",
        "created_at": "Sat Feb 28 04:34:30 +0000 2026",
        "lang": "en",
        "media": [
          {
            "type": "video",
            "id": "2027591228410265600",
            "url": "https://video.twimg.com/ext_tw_video/2027591228410265600/pu/vid/avc1/1080x1920/DK6aYdhGFr-KG8hJ.mp4?tag=19",
            "bitrate": 10368000
          }
        ],
        "retweet": null,
        "quoted": {
          "id": "2018214811260350716",
          "text": "Starbase has come a long way",
          "created_at": "Mon Feb 02 06:48:02 +0000 2026",
          "lang": "en",
          "media": [],
          "retweet": null,
          "quoted": null,
          "user": {
            "id": "44196397",
            "name": "Elon Musk",
            "screen_name": "elonmusk",
            "description": "",
            "followers_count": 235480169,
            "friends_count": 1290,
            "verified": false,
            "is_blue_verified": true
          },
          "stats": {
            "retweet_count": 11166,
            "favorite_count": 136393,
            "reply_count": 4419,
            "quote_count": 302
          }
        },
        "user": {
          "id": "1319287761048723458",
          "name": "Mario Nawfal",
          "screen_name": "MarioNawfal",
          "description": "Largest Show on X | 24x7 News | Investor 700+ Startups | Founder @ibcgroupio , https://t.co/sw7OQ5KOqu",
          "followers_count": 3086386,
          "friends_count": 50439,
          "verified": false,
          "is_blue_verified": true
        },
        "stats": {
          "retweet_count": 429,
          "favorite_count": 2929,
          "reply_count": 305,
          "quote_count": 36
        }
      },
      "quoted": null,
      "stats": {
        "retweet_count": 429,
        "favorite_count": 0,
        "reply_count": 0,
        "quote_count": 0
      }
    },
    {
      "id": "2027632419780891134",
      "text": "RT @Asmongold: @Pokket Because I think we need to have immigration law and deport illegal aliens?\n\nThere was an election, and this was a co…",
      "created_at": "Sat Feb 28 06:30:15 +0000 2026",
      "lang": "en",
      "media": [],
      "retweet": {
        "id": "2027605544887063004",
        "text": "@Pokket Because I think we need to have immigration law and deport illegal aliens?\n\nThere was an election, and this was a core issue people voted on\n\nIt's cringe as fuck seeing the privileged class of infulencers virtue signaling for something they never experience the consequences from",
        "created_at": "Sat Feb 28 04:43:27 +0000 2026",
        "lang": "en",
        "media": [],
        "retweet": null,
        "quoted": null,
        "user": {
          "id": "147039284",
          "name": "Zack",
          "screen_name": "Asmongold",
          "description": "Professional Neckbeard--Daily streams on https://t.co/BqNJkRKL0F and https://t.co/WHdqUUTp1E",
          "followers_count": 1259129,
          "friends_count": 1393,
          "verified": false,
          "is_blue_verified": true
        },
        "stats": {
          "retweet_count": 1288,
          "favorite_count": 28773,
          "reply_count": 571,
          "quote_count": 41
        }
      },
      "quoted": null,
      "stats": {
        "retweet_count": 1288,
        "favorite_count": 0,
        "reply_count": 0,
        "quote_count": 0
      }
    },
    {
      "id": "2027644868881957020",
      "text": "True",
      "created_at": "Sat Feb 28 07:19:43 +0000 2026",
      "lang": "en",
      "media": [],
      "retweet": null,
      "quoted": {
        "id": "2027434648800747845",
        "text": "To any future historians reading this, this era will make a lot more sense if you remember that every name is the opposite of what it really is. The antifascists are fascists, the antiracists are racists, the fact-checkers are propagandists, etc. Hopefully this has been fixed by your time.",
        "created_at": "Fri Feb 27 17:24:22 +0000 2026",
        "lang": "en",
        "media": [],
        "retweet": null,
        "quoted": null,
        "user": {
          "id": "243794322",
          "name": "Tristin Hopper",
          "screen_name": "TristinHopper",
          "description": "Columnist and reporter at National Post, Canada's only newspaper. Most influential person of Canada. Canada moral leader. Beloved Canadian role model",
          "followers_count": 42617,
          "friends_count": 7453,
          "verified": false,
          "is_blue_verified": true
        },
        "stats": {
          "retweet_count": 1775,
          "favorite_count": 11259,
          "reply_count": 414,
          "quote_count": 98
        }
      },
      "stats": {
        "retweet_count": 1109,
        "favorite_count": 10039,
        "reply_count": 1247,
        "quote_count": 65
      }
    },
    {
      "id": "2027804599772443017",
      "text": "RT @SawyerMerritt: 𝕏 just officially launched the For You timeline filter that allows you to only see posts about topics that you are inter…",
      "created_at": "Sat Feb 28 17:54:26 +0000 2026",
      "lang": "en",
      "media": [],
      "retweet": {
        "id": "2027787700300841137",
        "text": "𝕏 just officially launched the For You timeline filter that allows you to only see posts about topics that you are interested in. You can select multiple topics.\n\nTap the drop down menu button on “For You” at the top of your timeline to access it. https://t.co/9HumUDyTkw",
        "created_at": "Sat Feb 28 16:47:16 +0000 2026",
        "lang": "en",
        "media": [
          {
            "type": "photo",
            "id": "2027787697587204097",
            "url": "https://pbs.twimg.com/media/HCQmKtKXsAEK53A.jpg"
          }
        ],
        "retweet": null,
        "quoted": null,
        "user": {
          "id": "243013409",
          "name": "Sawyer Merritt",
          "screen_name": "SawyerMerritt",
          "description": "EV/space/tech news. Bringing you the latest news in a single, easy-to-read feed. $TSLA investor & Model Y owner.",
          "followers_count": 1043902,
          "friends_count": 433,
          "verified": false,
          "is_blue_verified": true
        },
        "stats": {
          "retweet_count": 153,
          "favorite_count": 1123,
          "reply_count": 195,
          "quote_count": 39
        }
      },
      "quoted": null,
      "stats": {
        "retweet_count": 153,
        "favorite_count": 0,
        "reply_count": 0,
        "quote_count": 0
      }
    },
    {
      "id": "2027804731343524008",
      "text": "You can now select topics for your timeline, so if you’re tired of political ragebait, you can select something else 😂\n\nJust tap on For You.",
      "created_at": "Sat Feb 28 17:54:57 +0000 2026",
      "lang": "en",
      "media": [],
      "retweet": null,
      "quoted": null,
      "stats": {
        "retweet_count": 1028,
        "favorite_count": 14061,
        "reply_count": 2838,
        "quote_count": 219
      }
    },
    {
      "id": "2027836581038465028",
      "text": "Prediction of the future is the best measure of intelligence",
      "created_at": "Sat Feb 28 20:01:30 +0000 2026",
      "lang": "en",
      "media": [],
      "retweet": null,
      "quoted": {
        "id": "2027813323761160355",
        "text": "Grok predicted the future accurately 🤯\n\nOn Feb 28 - the exact date Grok predicted - Israel & the US struck Iran\n\nThis wasn't a lucky guess. When pushed to predict, Grok analyzed geopolitical signals, Geneva talk outcomes, and real-time data to pinpoint the day\n\nGrok knows what the world thinks",
        "created_at": "Sat Feb 28 18:29:05 +0000 2026",
        "lang": "en",
        "media": [
          {
            "type": "photo",
            "id": "2027811779737489409",
            "url": "https://pbs.twimg.com/media/HCQ8EeKbEAE6EP-.jpg"
          }
        ],
        "retweet": null,
        "quoted": null,
        "user": {
          "id": "1818311005698678784",
          "name": "X Freeze",
          "screen_name": "XFreeze",
          "description": "",
          "followers_count": 158703,
          "friends_count": 1618,
          "verified": false,
          "is_blue_verified": true
        },
        "stats": {
          "retweet_count": 80,
          "favorite_count": 696,
          "reply_count": 112,
          "quote_count": 29
        }
      },
      "stats": {
        "retweet_count": 341,
        "favorite_count": 2759,
        "reply_count": 638,
        "quote_count": 39
      }
    },
    {
      "id": "2027838911964238231",
      "text": "If you’d like to see less politics or crypto, just select all except those ones.\n\nThis is an “early access” feature, so expect it to improve rapidly.",
      "created_at": "Sat Feb 28 20:10:46 +0000 2026",
      "lang": "en",
      "media": [],
      "retweet": null,
      "quoted": {
        "id": "2027822953052987604",
        "text": "an immediate improvement 🔥 https://t.co/SBl6oIstOd",
        "created_at": "Sat Feb 28 19:07:21 +0000 2026",
        "lang": "en",
        "media": [
          {
            "type": "photo",
            "id": "2027822948728639488",
            "url": "https://pbs.twimg.com/media/HCRGOl5bEAA3oBk.jpg"
          }
        ],
        "retweet": null,
        "quoted": null,
        "user": {
          "id": "1578127809792409616",
          "name": "Dan",
          "screen_name": "KettlebellDan",
          "description": "Hi I’m Dan a proud X employee and founder of the prestigious Kettlebell Krüe 🦾 Follow me for a daily X tip of the day for all of 2026",
          "followers_count": 84097,
          "friends_count": 1355,
          "verified": false,
          "is_blue_verified": true
        },
        "stats": {
          "retweet_count": 70,
          "favorite_count": 872,
          "reply_count": 190,
          "quote_count": 69
        }
      },
      "stats": {
        "retweet_count": 2310,
        "favorite_count": 24491,
        "reply_count": 4467,
        "quote_count": 437
      }
    },
    {
      "id": "2027878337016709409",
      "text": "Try Tesla self-driving",
      "created_at": "Sat Feb 28 22:47:26 +0000 2026",
      "lang": "en",
      "media": [],
      "retweet": null,
      "quoted": {
        "id": "2027477169954546135",
        "text": "FSD Supervised today is a completely different experience compared to earlier versions",
        "created_at": "Fri Feb 27 20:13:20 +0000 2026",
        "lang": "en",
        "media": [],
        "retweet": null,
        "quoted": null,
        "user": {
          "id": "13298072",
          "name": "Tesla",
          "screen_name": "Tesla",
          "description": "Electric vehicles, giant batteries & solar, AI & robotics",
          "followers_count": 24712813,
          "friends_count": 55,
          "verified": false,
          "is_blue_verified": true
        },
        "stats": {
          "retweet_count": 655,
          "favorite_count": 4697,
          "reply_count": 446,
          "quote_count": 39
        }
      },
      "stats": {
        "retweet_count": 1257,
        "favorite_count": 13552,
        "reply_count": 2420,
        "quote_count": 114
      }
    },
    {
      "id": "2027888598037463444",
      "text": "RT @mweinbach: First flight with starlink, this is so nice https://t.co/LHbKcAXl5I",
      "created_at": "Sat Feb 28 23:28:12 +0000 2026",
      "lang": "en",
      "media": [
        {
          "type": "photo",
          "id": "2027663292286595072",
          "url": "https://pbs.twimg.com/media/HCO1BXTXcAAKHms.jpg"
        }
      ],
      "retweet": {
        "id": "2027663298427072883",
        "text": "First flight with starlink, this is so nice https://t.co/LHbKcAXl5I",
        "created_at": "Sat Feb 28 08:32:57 +0000 2026",
        "lang": "en",
        "media": [
          {
            "type": "photo",
            "id": "2027663292286595072",
            "url": "https://pbs.twimg.com/media/HCO1BXTXcAAKHms.jpg"
          }
        ],
        "retweet": null,
        "quoted": null,
        "user": {
          "id": "3239896262",
          "name": "Max Weinbach",
          "screen_name": "mweinbach",
          "description": "Analyst @creativestrat | Analyst and Market Research Firm | Typo ignorer \nEmail: max@creativestrategies.com",
          "followers_count": 284975,
          "friends_count": 7222,
          "verified": false,
          "is_blue_verified": true
        },
        "stats": {
          "retweet_count": 168,
          "favorite_count": 1654,
          "reply_count": 151,
          "quote_count": 8
        }
      },
      "quoted": null,
      "stats": {
        "retweet_count": 168,
        "favorite_count": 0,
        "reply_count": 0,
        "quote_count": 0
      }
    },
    {
      "id": "2027889702712328619",
      "text": "Grok",
      "created_at": "Sat Feb 28 23:32:36 +0000 2026",
      "lang": "en",
      "media": [],
      "retweet": null,
      "quoted": {
        "id": "2027889344363593876",
        "text": "In times of split second decision making by our nation’s top leaders — it’s clear which AI our military should be using. \n\nTruth-seeking is @grok’s best feature. https://t.co/CTZbY4XhtT",
        "created_at": "Sat Feb 28 23:31:10 +0000 2026",
        "lang": "en",
        "media": [
          {
            "type": "photo",
            "id": "2027889340588630017",
            "url": "https://pbs.twimg.com/media/HCSCnG2WIAE_Ptg.jpg"
          }
        ],
        "retweet": null,
        "quoted": null,
        "user": {
          "id": "240504013",
          "name": "Katie Miller",
          "screen_name": "KatieMiller",
          "description": "@katiemillerpod available on YouTube, Spotify, Apple, Rumble, and of course X.",
          "followers_count": 208914,
          "friends_count": 893,
          "verified": false,
          "is_blue_verified": true
        },
        "stats": {
          "retweet_count": 357,
          "favorite_count": 2454,
          "reply_count": 491,
          "quote_count": 99
        }
      },
      "stats": {
        "retweet_count": 2639,
        "favorite_count": 21311,
        "reply_count": 3106,
        "quote_count": 231
      }
    }
  ]
}