{
  "user": {
    "screen_name": "elonmusk",
    "name": "Elon Musk",
    "description": "",
    "followers_count": 235924868,
    "verified": false,
    "is_blue_verified": true
  },
  "date": "20260305",
  "last_updated": "2026-03-05T02:59:00.774178",
  "tweet_count": 9,
  "tweets": [
    {
      "id": "2029358863921889377",
      "text": "RT @dvorahfr: Hatching a chick in 3 ten-second sequences with the Grok Imagine extension https://t.co/VMCv333Glg",
      "created_at": "Thu Mar 05 00:50:31 +0000 2026",
      "lang": "en",
      "media": [
        {
          "type": "video",
          "id": "2029248499947323395",
          "url": "https://video.twimg.com/amplify_video/2029248499947323395/vid/avc1/720x720/ZfZrP2ltqIfnX247.mp4?tag=24",
          "bitrate": 10368000
        }
      ],
      "retweet": {
        "id": "2029254546271465594",
        "text": "Hatching a chick in 3 ten-second sequences with the Grok Imagine extension https://t.co/VMCv333Glg",
        "created_at": "Wed Mar 04 17:56:00 +0000 2026",
        "lang": "en",
        "media": [
          {
            "type": "video",
            "id": "2029248499947323395",
            "url": "https://video.twimg.com/amplify_video/2029248499947323395/vid/avc1/720x720/ZfZrP2ltqIfnX247.mp4?tag=24",
            "bitrate": 10368000
          }
        ],
        "retweet": null,
        "quoted": null,
        "user": {
          "id": "2178040394",
          "name": "Déborah",
          "screen_name": "dvorahfr",
          "description": "Exhibition of my AI Illustrations and videos  by Grok Imagine and Art of all kinds!\n Follow me for Art",
          "followers_count": 118386,
          "friends_count": 3458,
          "verified": false,
          "is_blue_verified": true
        },
        "stats": {
          "retweet_count": 238,
          "favorite_count": 1293,
          "reply_count": 205,
          "quote_count": 13
        }
      },
      "quoted": null,
      "stats": {
        "retweet_count": 238,
        "favorite_count": 0,
        "reply_count": 0,
        "quote_count": 0
      }
    },
    {
      "id": "2029359835456913459",
      "text": "RT @cb_doge: BREAKING: Grokipedia traffic is up 52.61% as compared to last month. 🔥 https://t.co/OHRonco8vl",
      "created_at": "Thu Mar 05 00:54:23 +0000 2026",
      "lang": "en",
      "media": [
        {
          "type": "photo",
          "id": "2028838110906269696",
          "url": "https://pbs.twimg.com/media/HCfhgztXwAApoy7.jpg"
        }
      ],
      "retweet": {
        "id": "2028838339647013122",
        "text": "BREAKING: Grokipedia traffic is up 52.61% as compared to last month. 🔥 https://t.co/OHRonco8vl",
        "created_at": "Tue Mar 03 14:22:08 +0000 2026",
        "lang": "en",
        "media": [
          {
            "type": "photo",
            "id": "2028838110906269696",
            "url": "https://pbs.twimg.com/media/HCfhgztXwAApoy7.jpg"
          }
        ],
        "retweet": null,
        "quoted": null,
        "user": {
          "id": "1389913567671975937",
          "name": "DogeDesigner",
          "screen_name": "cb_doge",
          "description": "",
          "followers_count": 1842445,
          "friends_count": 908,
          "verified": false,
          "is_blue_verified": true
        },
        "stats": {
          "retweet_count": 412,
          "favorite_count": 2561,
          "reply_count": 404,
          "quote_count": 29
        }
      },
      "quoted": null,
      "stats": {
        "retweet_count": 412,
        "favorite_count": 0,
        "reply_count": 0,
        "quote_count": 0
      }
    },
    {
      "id": "2029372985547866170",
      "text": "Cool",
      "created_at": "Thu Mar 05 01:46:38 +0000 2026",
      "lang": "en",
      "media": [],
      "retweet": null,
      "quoted": {
        "id": "2028947781990400274",
        "text": "Grok Heavy one-shotted the full C code gen!\nhttps://t.co/9AuMdrqYUp",
        "created_at": "Tue Mar 03 21:37:01 +0000 2026",
        "lang": "en",
        "media": [
          {
            "type": "video",
            "id": "1956611529568391169",
            "url": "https://video.twimg.com/amplify_video/1956611529568391169/vid/avc1/1902x1080/8CFCKHst2r8kjlFN.mp4?tag=21",
            "bitrate": 10368000
          }
        ],
        "retweet": null,
        "quoted": null,
        "user": {
          "id": "1587601034339561472",
          "name": "tetsuo",
          "screen_name": "tetsuoai",
          "description": "code since '94 · C · asm · AI & art via grok · @tetsuocorp · @7etsuo · @a_g_e_n_c",
          "followers_count": 230353,
          "friends_count": 980,
          "verified": false,
          "is_blue_verified": true
        },
        "stats": {
          "retweet_count": 153,
          "favorite_count": 1970,
          "reply_count": 132,
          "quote_count": 31
        }
      },
      "stats": {
        "retweet_count": 890,
        "favorite_count": 12440,
        "reply_count": 918,
        "quote_count": 50
      }
    },
    {
      "id": "2029373372883452027",
      "text": "Grok Imagine improves again",
      "created_at": "Thu Mar 05 01:48:10 +0000 2026",
      "lang": "en",
      "media": [],
      "retweet": null,
      "quoted": {
        "id": "2029368045597057426",
        "text": "Once upon a time...Grok Imagine https://t.co/DTshWuADXB",
        "created_at": "Thu Mar 05 01:27:00 +0000 2026",
        "lang": "en",
        "media": [
          {
            "type": "video",
            "id": "2029367999665160192",
            "url": "https://video.twimg.com/ext_tw_video/2029367999665160192/pu/vid/avc1/720x1072/DIZ15Fh8I8beo9ud.mp4?tag=22",
            "bitrate": 10368000
          }
        ],
        "retweet": null,
        "quoted": null,
        "user": {
          "id": "2178040394",
          "name": "Déborah",
          "screen_name": "dvorahfr",
          "description": "Exhibition of my AI Illustrations and videos  by Grok Imagine and Art of all kinds!\n Follow me for Art",
          "followers_count": 118386,
          "friends_count": 3458,
          "verified": false,
          "is_blue_verified": true
        },
        "stats": {
          "retweet_count": 65,
          "favorite_count": 429,
          "reply_count": 123,
          "quote_count": 13
        }
      },
      "stats": {
        "retweet_count": 758,
        "favorite_count": 7366,
        "reply_count": 1570,
        "quote_count": 55
      }
    },
    {
      "id": "2029376228189438128",
      "text": "Grok Video🥇",
      "created_at": "Thu Mar 05 01:59:31 +0000 2026",
      "lang": "en",
      "media": [],
      "retweet": null,
      "quoted": {
        "id": "2029375140933329035",
        "text": "Grok Imagine Video officially ranks #1 on the Arena Image-to-Video Leaderboard, completely dominating Google Veo 3.1 and every other model on the market https://t.co/43zmXG3ejt",
        "created_at": "Thu Mar 05 01:55:12 +0000 2026",
        "lang": "en",
        "media": [
          {
            "type": "photo",
            "id": "2029374367650488320",
            "url": "https://pbs.twimg.com/media/HCnJPDwXIAAYDo_.jpg"
          }
        ],
        "retweet": null,
        "quoted": null,
        "user": {
          "id": "1818311005698678784",
          "name": "X Freeze",
          "screen_name": "XFreeze",
          "description": "",
          "followers_count": 162529,
          "friends_count": 1639,
          "verified": false,
          "is_blue_verified": true
        },
        "stats": {
          "retweet_count": 39,
          "favorite_count": 182,
          "reply_count": 93,
          "quote_count": 14
        }
      },
      "stats": {
        "retweet_count": 617,
        "favorite_count": 4833,
        "reply_count": 1034,
        "quote_count": 41
      }
    },
    {
      "id": "2029379085638791195",
      "text": "Easy to make cool videos with @Grok\n\nhttps://t.co/u2y4RZSsOD",
      "created_at": "Thu Mar 05 02:10:52 +0000 2026",
      "lang": "en",
      "media": [],
      "retweet": null,
      "quoted": {
        "id": "2028737230844710988",
        "text": "Gn, 𝕏..·˚ ༘ ☾ ⋆｡˚ ☄︎\n\nGrok Imagine \"extend from frame\" 30 second continuous video.💫 https://t.co/XHrdpXhnZA",
        "created_at": "Tue Mar 03 07:40:22 +0000 2026",
        "lang": "en",
        "media": [
          {
            "type": "video",
            "id": "2028735874113138688",
            "url": "https://video.twimg.com/amplify_video/2028735874113138688/vid/avc1/752x416/Oens9gzffUbyK7B2.mp4?tag=24",
            "bitrate": 5184000
          }
        ],
        "retweet": null,
        "quoted": null,
        "user": {
          "id": "1587601034339561472",
          "name": "tetsuo",
          "screen_name": "tetsuoai",
          "description": "code since '94 · C · asm · AI & art via grok · @tetsuocorp · @7etsuo · @a_g_e_n_c",
          "followers_count": 230353,
          "friends_count": 980,
          "verified": false,
          "is_blue_verified": true
        },
        "stats": {
          "retweet_count": 36,
          "favorite_count": 360,
          "reply_count": 62,
          "quote_count": 8
        }
      },
      "stats": {
        "retweet_count": 423,
        "favorite_count": 3182,
        "reply_count": 800,
        "quote_count": 39
      }
    },
    {
      "id": "2029379176273490414",
      "text": "One day ♥️",
      "created_at": "Thu Mar 05 02:11:14 +0000 2026",
      "lang": "en",
      "media": [],
      "retweet": null,
      "quoted": {
        "id": "2029268589711376617",
        "text": "This picture was taken on Mars recently. https://t.co/JUaDR49vhg",
        "created_at": "Wed Mar 04 18:51:48 +0000 2026",
        "lang": "en",
        "media": [
          {
            "type": "photo",
            "id": "2029268585718398981",
            "url": "https://pbs.twimg.com/media/HClpBvWawAUlWZ2.jpg"
          }
        ],
        "retweet": null,
        "quoted": null,
        "user": {
          "id": "1389913567671975937",
          "name": "DogeDesigner",
          "screen_name": "cb_doge",
          "description": "",
          "followers_count": 1842445,
          "friends_count": 908,
          "verified": false,
          "is_blue_verified": true
        },
        "stats": {
          "retweet_count": 184,
          "favorite_count": 1645,
          "reply_count": 698,
          "quote_count": 41
        }
      },
      "stats": {
        "retweet_count": 1734,
        "favorite_count": 30908,
        "reply_count": 3312,
        "quote_count": 140
      }
    },
    {
      "id": "2029379342002987127",
      "text": "RT @wil_da_beast630: 99.1% were men. \n\nA bizarrely missed feminist opportunity is pointing out that 85% of violent criminals are dudes.\n\nIn…",
      "created_at": "Thu Mar 05 02:11:53 +0000 2026",
      "lang": "en",
      "media": [],
      "retweet": {
        "id": "2029375751754055857",
        "text": "99.1% were men. \n\nA bizarrely missed feminist opportunity is pointing out that 85% of violent criminals are dudes.\n\nInventors too, though.",
        "created_at": "Thu Mar 05 01:57:37 +0000 2026",
        "lang": "en",
        "media": [],
        "retweet": null,
        "quoted": {
          "id": "2029273690790035615",
          "text": "According to the United States Sentencing Commission, 71.2% of individuals sentenced for child p*rnography were White men, 18% were Hispanic men, 6% were Black men, and 4.8% were other races. \n\nIn conclusion, men, especially White men are the problem. https://t.co/QZBdotKyzq",
          "created_at": "Wed Mar 04 19:12:04 +0000 2026",
          "lang": "en",
          "media": [
            {
              "type": "photo",
              "id": "2029273687879499779",
              "url": "https://pbs.twimg.com/media/HCltquYawAM68EF.jpg"
            }
          ],
          "retweet": null,
          "quoted": null,
          "user": {
            "id": "1697523547726290944",
            "name": "Nora",
            "screen_name": "Heal_within96",
            "description": "Muslim first. Pan-African. An advocate for uncomfortable truths over soft lies, resilience and self-agency.",
            "followers_count": 8882,
            "friends_count": 767,
            "verified": false,
            "is_blue_verified": true
          },
          "stats": {
            "retweet_count": 173,
            "favorite_count": 370,
            "reply_count": 100,
            "quote_count": 26
          }
        },
        "user": {
          "id": "1011008340367953920",
          "name": "Wilfred Reilly",
          "screen_name": "wil_da_beast630",
          "description": "A college professor now, I am a former corporate executive, freedom rider, law student, and poor kid. Butlerian Jihad Advocate. Karen Appreciator.",
          "followers_count": 169961,
          "friends_count": 3684,
          "verified": false,
          "is_blue_verified": true
        },
        "stats": {
          "retweet_count": 162,
          "favorite_count": 739,
          "reply_count": 174,
          "quote_count": 7
        }
      },
      "quoted": null,
      "stats": {
        "retweet_count": 162,
        "favorite_count": 0,
        "reply_count": 0,
        "quote_count": 0
      }
    },
    {
      "id": "2029384571788407254",
      "text": "Grok can watch videos for you",
      "created_at": "Thu Mar 05 02:32:40 +0000 2026",
      "lang": "en",
      "media": [],
      "retweet": null,
      "quoted": {
        "id": "2029375186064294297",
        "text": "One of the most underrated features of Grok is its ability to summarize long videos for you.\n\nDrop in a video and get the summary in seconds.\n\nTry it now!\n\n https://t.co/XjWUIYcK36",
        "created_at": "Thu Mar 05 01:55:22 +0000 2026",
        "lang": "en",
        "media": [
          {
            "type": "video",
            "id": "2014493721509724160",
            "url": "https://video.twimg.com/amplify_video/2014493721509724160/vid/avc1/1080x1080/EX2N3JbhMAcqdHh7.mp4?tag=21",
            "bitrate": 8768000
          }
        ],
        "retweet": null,
        "quoted": null,
        "user": {
          "id": "1389913567671975937",
          "name": "DogeDesigner",
          "screen_name": "cb_doge",
          "description": "",
          "followers_count": 1842445,
          "friends_count": 908,
          "verified": false,
          "is_blue_verified": true
        },
        "stats": {
          "retweet_count": 50,
          "favorite_count": 284,
          "reply_count": 100,
          "quote_count": 15
        }
      },
      "stats": {
        "retweet_count": 485,
        "favorite_count": 3176,
        "reply_count": 1041,
        "quote_count": 47
      }
    }
  ]
}